odoo/addons/pattern_import_export/.gitignore
odoo/addons/pattern_import_export/README.rst
odoo/addons/pattern_import_export/__init__.py
odoo/addons/pattern_import_export/__manifest__.py
odoo/addons/pattern_import_export/data/queue_job_channel_data.xml
odoo/addons/pattern_import_export/data/queue_job_function_data.xml
odoo/addons/pattern_import_export/demo/demo.xml
odoo/addons/pattern_import_export/i18n/pattern_import_export.pot
odoo/addons/pattern_import_export/migrations/12.0.3.0.0/pre-migrate.py
odoo/addons/pattern_import_export/migrations/12.0.4.0.0/post-migrate.py
odoo/addons/pattern_import_export/migrations/12.0.4.0.0/pre-migrate.py
odoo/addons/pattern_import_export/models/__init__.py
odoo/addons/pattern_import_export/models/base.py
odoo/addons/pattern_import_export/models/common.py
odoo/addons/pattern_import_export/models/ir_actions.py
odoo/addons/pattern_import_export/models/ir_attachment.py
odoo/addons/pattern_import_export/models/ir_exports.py
odoo/addons/pattern_import_export/models/ir_exports_line.py
odoo/addons/pattern_import_export/models/ir_fields.py
odoo/addons/pattern_import_export/models/patch.py
odoo/addons/pattern_import_export/models/pattern_chunk.py
odoo/addons/pattern_import_export/models/pattern_config.py
odoo/addons/pattern_import_export/models/pattern_file.py
odoo/addons/pattern_import_export/readme/CONFIGURE.rst
odoo/addons/pattern_import_export/readme/CONTRIBUTORS.rst
odoo/addons/pattern_import_export/readme/DESCRIPTION.rst
odoo/addons/pattern_import_export/readme/ROADMAP.rst
odoo/addons/pattern_import_export/readme/USAGE.rst
odoo/addons/pattern_import_export/security/ir.model.access.csv
odoo/addons/pattern_import_export/security/pattern_security.xml
odoo/addons/pattern_import_export/static/description/icon.png
odoo/addons/pattern_import_export/static/description/index.html
odoo/addons/pattern_import_export/tests/__init__.py
odoo/addons/pattern_import_export/tests/common.py
odoo/addons/pattern_import_export/tests/test_converter.py
odoo14_addon_pattern_import_export-14.0.2.9.0.dist-info/METADATA
odoo14_addon_pattern_import_export-14.0.2.9.0.dist-info/WHEEL
odoo14_addon_pattern_import_export-14.0.2.9.0.dist-info/top_level.txt
odoo14_addon_pattern_import_export-14.0.2.9.0.dist-info/RECORD
