Metadata-Version: 2.1
Name: odoo14-addon-pattern-import-export
Version: 14.0.2.9.0
Summary: Pattern for import or export
Home-page: https://github.com/Shopinvader/pattern-import-export
Author: Akretion
License: AGPL-3
Platform: UNKNOWN
Classifier: Programming Language :: Python
Classifier: Framework :: Odoo
Classifier: Framework :: Odoo :: 14.0
Classifier: License :: OSI Approved :: GNU Affero General Public License v3
Requires-Python: >=3.6
Requires-Dist: odoo14-addon-base-export-manager
Requires-Dist: odoo14-addon-base-sparse-field-list-support
Requires-Dist: odoo14-addon-jsonifier
Requires-Dist: odoo14-addon-queue-job
Requires-Dist: odoo14-addon-web-notify
Requires-Dist: odoo <14.1dev,>=14.0a
